pygremlinbox_hippocratic_2_1/__init__.py
pygremlinbox_hippocratic_2_1-1.4.0.dist-info/licenses/LICENCE
pygremlinbox_hippocratic_2_1-1.4.0.dist-info/METADATA
pygremlinbox_hippocratic_2_1-1.4.0.dist-info/WHEEL
pygremlinbox_hippocratic_2_1-1.4.0.dist-info/top_level.txt
pygremlinbox_hippocratic_2_1-1.4.0.dist-info/RECORD
